megatron_11b/__init__.py
megatron_11b/configuration_megatron.py
megatron_11b/convert_megatron_original_pytorch_checkpoint_to_pytorch.py
megatron_11b/megatron_policy.py
megatron_11b/modeling_megatron.py
megatron_11b/tokenization_megatron.py
megatron_11b/tokenization_megatron_fast.py
tests/__init__.py
tests/parallelism.py
megatron_11b-1.2.dist-info/METADATA
megatron_11b-1.2.dist-info/WHEEL
megatron_11b-1.2.dist-info/top_level.txt
megatron_11b-1.2.dist-info/RECORD
